jentic/apitools/openapi/transformer/bundler/backends/base.py
jentic/apitools/openapi/transformer/bundler/backends/default.py
jentic/apitools/openapi/transformer/bundler/backends/py.typed
jentic/apitools/openapi/transformer/bundler/core/__init__.py
jentic/apitools/openapi/transformer/bundler/core/bundler.py
jentic/apitools/openapi/transformer/bundler/core/py.typed
jentic/apitools/openapi/transformer/core/__init__.py
jentic/apitools/openapi/transformer/core/normalize.py
jentic/apitools/openapi/transformer/core/references.py
jentic_openapi_transformer-1.0.0a34.dist-info/licenses/LICENSE
jentic_openapi_transformer-1.0.0a34.dist-info/licenses/NOTICE
jentic_openapi_transformer-1.0.0a34.dist-info/WHEEL
jentic_openapi_transformer-1.0.0a34.dist-info/entry_points.txt
jentic_openapi_transformer-1.0.0a34.dist-info/METADATA
jentic_openapi_transformer-1.0.0a34.dist-info/RECORD
